md5dir/__init__.py
md5dir/md5dir.py
md5dir-0.2.6.dist-info/LICENCE
md5dir-0.2.6.dist-info/METADATA
md5dir-0.2.6.dist-info/WHEEL
md5dir-0.2.6.dist-info/entry_points.txt
md5dir-0.2.6.dist-info/top_level.txt
md5dir-0.2.6.dist-info/RECORD
