Metadata-Version: 2.1
Name: md5dir
Version: 0.2.6
Summary: Compute the md5 sum of a directory
Home-page: http://github.com/machinbrol/md5dir
Author: MachinBrol
Author-email: zazor@riseup.net
License: WTFPL
Platform: UNKNOWN
Classifier: Programming Language :: Python
Classifier: Natural Language :: French
Requires-Dist: click
